<?xml version="1.0"?>
<!-- Generated by the OpenACS Package Manager -->

<package key="cams" url="http://openacs.org/repository/apm/packages/cams" type="apm_application">
    <package-name>Content Manager</package-name>
    <pretty-plural>Content Managers</pretty-plural>
    <initial-install-p>f</initial-install-p>
    <singleton-p>t</singleton-p>
    <auto-mount>/cams/</auto-mount>

    <version name="0.5" url="http://openacs.org/repository/download/apm/cams-0.5.apm">
        <owner url="mailto:tom@rmadilo.com">Tom Jackson</owner>
        <summary>Content Application Management System</summary>
        <description format="text/plain">Allows generic and rapid development of content based applications. </description>

        <provides url="cams" version="0.5"/>

        <callbacks>
        </callbacks>
        <parameters>
            <parameter datatype="string"  min_n_values="1"  max_n_values="1"  name="ContentTemplate"  default="content" description="Content Template to use when none is specified."/>
            <parameter datatype="string"  min_n_values="1"  max_n_values="1"  name="ContentTemplateTypeId"  description="Content Type Id where Content Templates are stored."/>
            <parameter datatype="string"  min_n_values="1"  max_n_values="1"  name="ContentTypeTemplate"  default="one" description="Content Type template to use when none is specified."/>
            <parameter datatype="string"  min_n_values="1"  max_n_values="1"  name="ContentTypeTemplateTypeId"  description="Content Type Id where Content Type Templates are stored."/>
            <parameter datatype="string"  min_n_values="1"  max_n_values="1"  name="MasterTemplate"  description="Master template to use when none is defined"/>
            <parameter datatype="string"  min_n_values="1"  max_n_values="1"  name="MasterTemplateTypeId"  description="Content Type Id where Master templates are stored."/>
        </parameters>

    </version>
</package>
